AUTHORS
CHANGELOG
COPYING
MANIFEST.in
Makefile
README
setup.py
stdeb.cfg
Axon/AdaptiveCommsComponent.py
Axon/AxonExceptions.py
Axon/Base.py
Axon/Box.py
Axon/Component.py
Axon/CoordinatingAssistantTracker.py
Axon/Handle.py
Axon/Introspector.py
Axon/Ipc.py
Axon/Linkage.py
Axon/Microprocess.py
Axon/Postoffice.py
Axon/STM.py
Axon/Scheduler.py
Axon/ThreadedComponent.py
Axon/__init__.py
Axon/background.py
Axon/debug.conf
Axon/debug.py
Axon/debugConfigDefaults.py
Axon/debugConfigFile.py
Axon/idGen.py
Axon/util.py
Axon/experimental/Process.py
Axon/experimental/_pprocess_support.py
Axon/test/README
Examples/SystemShutdown.py
Examples/Handles/TestHandle.py
Examples/Handles/reverser.py
Examples/Immortalise/Crasher.py
Examples/STM/Axon.Philosophers.py
Examples/STM/Philosophers.py
Examples/Simple/README.py
Examples/Simple/all.py
Examples/SynchronousLinks/basic_syncLinksAcceptanceTest.py
kamaelia_axon.egg-info/PKG-INFO
kamaelia_axon.egg-info/SOURCES.txt
kamaelia_axon.egg-info/dependency_links.txt
kamaelia_axon.egg-info/top_level.txt