Metadata-Version: 2.1
Name: kamaelia-axon
Version: 1.14.32
Summary: Axon - Asynchronous Isolated Generator Component System
Home-page: http://www.kamaelia.org/
Author: Michael Sparks (sparkslabs)
Author-email: sparks.m@gmail.com
License: Apache Software License
License-File: COPYING
License-File: AUTHORS
